{
  "welcomeMessage": "Logged In User , {{ UserName }}! It's great to have you!",
  "dashboard": {
    "firstName": "First Name",
    "secondName": "Second Name",
    "gender": "Gender",
    "location": "Location",
    "governate": "Governante",
    "administrationArea": "Administration Area",
    "locality": "Locality",
    "personPlace": "Person Place",
    "hearedBy": "Heared By",
    "caseType": "Case Type",
    "career": "Person Career",
    "socialSituation": "Social Situation",
    "aconmySituation": "Aconmy Situation",
    "healthSitutation": "Health Situation",
    "nationality": "Nationality",
    "personLang": "Person Language",
    "ageViolate": "Violate Age",
    "fullName": "Full Name",
    "idNumber": "Id Number",
    "establishment": "Establishment"
  },
  "maincatogries": {
    "economicExploitation": "Economic Exploitation",
    "abusViolence": "Abus Violence",
    "displacement": "Homelessness",
    "sexualThings": "Sexual Things",
    "mentalPsychologicalHealth": "Mental Psychological Health",
    "narcoticSubstances": "Narcotic Substances",
    "studyMatters": "Study Matters",
    "discrimination": "Discrimination",
    "Specialseeds": "Specials Needs",
    "requiringInformation": "Requiring Information",
    "peerRelationships": "Peer Relationships",
    "familyRelations": "Family Relations",
    "legalIssues": "Legal Issues",
    "armedConflict": "Armed Conflict"
  },
  "subCatogries": {
    "medicalConsultation": "Medical Consultation",
    "inquiriesDiseases": "Inquiries Diseases",
    "hospitalAdmission": "Hospital Admission",
    "healthCare": "healthCare",
    "selfHarming": "Self Harming",
    "secretsDisclosure": "Secrets Disclosure",
    "depression": "Depression",
    "suicide": "Suicide",
    "obsessive": "Obsessive",
    "stealing": "Stealing",
    "nervousness": "Nervousness",
    "schizophrenia": "Schizophrenia",
    "fear": "Fear",
    "lying": "Lying",
    "adolescence": "Adolescence",
    "psychologicalDischarge": "Psychological Discharge",
    "boredom": "Boredom",
    "lifeEnd": "Life End",
    "autism": "Autism",
    "peeReflex": "Pee Reflex",
    "LowSelfEsteem": "Low Self Esteem",
    "threat": "Threat",
    "deathThreat": "Death Threat",
    "economicDeprivation": "Economic Deprivation",
    "control": "Control",
    "anorexia": "Anorexia",
    "nailBiting": "Nail Biting",
    "nightmares": "Nightmares",
    "speechProblems": "Speech Problems",
    "helpThanks": "Help Thanks",
    "line": "Lines",
    "volunteer": "Volunteer",
    "childrenHelp": "Children Help",
    "professional": "professional"
  }
}
